{
  "slug": "2026-05-18",
  "generatedAt": "2026-05-18T12:40:48.957Z",
  "article": {
    "title": "Security researcher says Microsoft built a Bitlocker backdoor, releases exploit",
    "url": "https://www.techspot.com/news/112410-security-researcher-microsoft-secretly-built-backdoor-bitlocker-releases.html",
    "source": "techspot.com",
    "selectedAt": "2026-05-18T12:40:40.404Z",
    "publishedAt": "2026-05-17T13:42:30.000Z",
    "hn": {
      "id": 48168856,
      "score": 571,
      "comments": 258
    }
  },
  "takeaways": [],
  "summary": "A security researcher has revealed that Microsoft incorporated a backdoor into its BitLocker encryption software, subsequently publishing a working exploit. This discovery raises significant concerns about the integrity of BitLocker’s security and the potential for unauthorized access to encrypted data.",
  "keyPoints": [
    "Microsoft allegedly built a secret backdoor into BitLocker, its full-disk encryption tool.",
    "The researcher publicly released a functional exploit demonstrating how the backdoor can be leveraged.",
    "BitLocker is widely used in Windows environments to protect sensitive data via encryption.",
    "This backdoor undermines trust in BitLocker’s security guarantees and may expose users to data breaches.",
    "The revelation could prompt organizations to reevaluate their reliance on BitLocker for data protection."
  ],
  "rewrite": {
    "title": "Researcher Uncovers Microsoft BitLocker Backdoor Exploit",
    "body": "A recent disclosure by a security researcher has uncovered a covert backdoor embedded within Microsoft’s BitLocker encryption software, along with a released exploit that demonstrates how this vulnerability can be exploited. BitLocker, a critical component of Windows security, is designed to protect data through full-disk encryption, and its integrity is paramount for enterprise and personal users alike. The existence of a backdoor fundamentally compromises the trust placed in BitLocker, as it potentially allows unauthorized parties to bypass encryption safeguards and access protected data.\n\nThe exploit’s public release intensifies concerns about the security of encrypted Windows devices, especially in sectors where data confidentiality is crucial. Organizations relying heavily on BitLocker for compliance and protection may need to reassess their security posture and consider alternative encryption solutions or additional protective measures. This development also highlights the broader risks associated with proprietary encryption tools where backdoors can be secretly introduced.\n\nWhile Microsoft has not officially commented on the claims, the implications are far-reaching, potentially affecting millions of users worldwide. The incident underscores the importance of transparency and independent security audits in cryptographic software to prevent hidden vulnerabilities that could be exploited by malicious actors or state-level adversaries.",
    "disclaimer": "AI-assisted rewrite based on extracted text + discussion signals"
  },
  "highlights": [],
  "meta": {
    "extract": {
      "ok": false,
      "chars": 0
    },
    "ai": {
      "enabled": true,
      "generated": true
    }
  }
}
